Workbook

Sheet 【コピー用】請求書 
B1: 請 求 書
B3: スズキサトミ | F3: 御中 | H3: 発行日 | J3: 46152
H4: 登録番号 | J4: -
H6: 氏名：
H7: 郵便番号：
B8: 下記のとおり御請求申し上げます。 | H8: 住所：
B10: ご請求金額 | E10: （税込） | H10: TEL :
B12: お支払期限 | D12: 46162
B14: No. | C14: 品 名 | E14: 数量 | F14: 単位 | G14: 単価 | H14: 金 額 | J14: 摘要
B15: 1
B16: 2
B17: 3
B18: 4
B19: 5
B20: 6
B21: 7
B22: 8
B23: 9
B24: 10
B25: 11
B26: 12
... B28: 14
B29: 15 | H29: =ROUND(E29*G29,0) -> 0
B30: 16 | H30: =ROUND(E30*G30,0) -> 0
B31: 17 | H31: =ROUND(E31*G31,0) -> 0
B32: 18 | H32: =ROUND(E32*G32,0) -> 0
B33: 19 | H33: =ROUND(E33*G33,0) -> 0
B34: 20 | H34: =ROUND(E34*G34,0) -> 0
B35: 21 | H35: =ROUND(E35*G35,0) -> 0
B36: 22 | H36: =ROUND(E36*G36,0) -> 0
B37: 23 | H37: =ROUND(E37*G37,0) -> 0
B39: [振込先] | G39: 合 計 | H39: =SUM(H15:H37) -> 0
C40: 普通
C42: 名義

Sheet 【記入例】請求書
B1: 請 求 書
B3: スズキサトミ | F3: 御中 | H3: 発行日 | I3: 45787
H4: 登録番号
H6: お名前
H7: ご住所
B8: 下記のとおり御請求申し上げます。
B10: ご請求金額 | D10: =H34 -> 18635 | E10: （税込） | H10: TEL :
B12: お支払期限 | D12: 45797
B14: No. | C14: 品 名 | E14: 数量 | F14: 単位 | G14: 単価 | H14: 金 額 | I14: 摘要
B15: 1 | C15: リタイアchNo132原稿 | E15: 1 | F15: 件 | G15: 3000 | H15: =ROUND(E15*G15,0) -> 3000
B16: 2 | C16: リタイアchNo132のサムネ・タイトル | E16: 1 | F16: 件 | G16: 500 | H16: =ROUND(E16*G16,0) -> 500
B17: 3 | C17: リタイアchNo133原稿 | E17: 1 | F17: 件 | G17: 5456 | H17: =ROUND(E17*G17,0) -> 5456
B18: 4 | C18: リタイアchNo133のサムネ・タイトル | E18: 1 | F18: 件 | G18: 500 | H18: =ROUND(E18*G18,0) -> 500
B19: 5 | C19: リタイアchNo134原稿 | E19: 1 | F19: 件 | G19: 3000 | H19: =ROUND(E19*G19,0) -> 3000
B20: 6 | C20: リタイアchNo134のサムネ・タイトル | E20: 1 | F20: 件 | G20: 500 | H20: =ROUND(E20*G20,0) -> 500
B21: =IF(C21="","",1+B20) -> 7 | C21: リタイアchNo135原稿 | E21: 1 | F21: 件 | G21: 5179 | H21: =ROUND(E21*G21,0) -> 5179
B22: =IF(C22="","",1+B21) -> 8 | C22: リタイアchNo135のサムネ・タイトル | E22: 1 | F22: 件 | G22: 500 | H22: =ROUND(E22*G22,0) -> 500
B23: =IF(C23="","",1+B22) | G23: =IF(ISERROR(VLOOKUP(C23,'マスタ設定'!$E$9:$F$31,2,FALSE)),"",VLOOKUP(C23,'マスタ設定'!$E$9:$F$31,2,FALSE)) | H23: =ROUND(E23*G23,0) -> 0
B24: =IF(C24="","",1+B23) | G24: =IF(ISERROR(VLOOKUP(C24,'マスタ設定'!$E$9:$F$31,2,FALSE)),"",VLOOKUP(C24,'マスタ設定'!$E$9:$F$31,2,FALSE)) | H24: =ROUND(E24*G24,0) -> 0
B25: =IF(C25="","",1+B24) | G25: =IF(ISERROR(VLOOKUP(C25,'マスタ設定'!$E$9:$F$31,2,FALSE)),"",VLOOKUP(C25,'マスタ設定'!$E$9:$F$31,2,FALSE)) | H25: =ROUND(E25*G25,0) -> 0
B26: =IF(C26="","",1+B25) | G26: =IF(ISERROR(VLOOKUP(C26,'マスタ設定'!$E$9:$F$31,2,FALSE)),"",VLOOKUP(C26,'マスタ設定'!$E$9:$F$31,2,FALSE)) | H26: =ROUND(E26*G26,0) -> 0
B27: =IF(C27="","",1+B26) | G27: =IF(ISERROR(VLOOKUP(C27,'マスタ設定'!$E$9:$F$31,2,FALSE)),"",VLOOKUP(C27,'マスタ設定'!$E$9:$F$31,2,FALSE)) | H27: =ROUND(E27*G27,0) -> 0
B28: =IF(C28="","",1+B27) | G28: =IF(ISERROR(VLOOKUP(C28,'マスタ設定'!$E$9:$F$31,2,FALSE)),"",VLOOKUP(C28,'マスタ設定'!$E$9:$F$31,2,FALSE)) | H28: =ROUND(E28*G28,0) -> 0
B29: =IF(C29="","",1+B28) | G29: =IF(ISERROR(VLOOKUP(C29,'マスタ設定'!$E$9:$F$31,2,FALSE)),"",VLOOKUP(C29,'マスタ設定'!$E$9:$F$31,2,FALSE)) | H29: =ROUND(E29*G29,0) -> 0
B30: =IF(C30="","",1+B29) | G30: =IF(ISERROR(VLOOKUP(C30,'マスタ設定'!$E$9:$F$31,2,FALSE)),"",VLOOKUP(C30,'マスタ設定'!$E$9:$F$31,2,FALSE)) | H30: =ROUND(E30*G30,0) -> 0
B31: =IF(C31="","",1+B30) | G31: =IF(ISERROR(VLOOKUP(C31,'マスタ設定'!$E$9:$F$31,2,FALSE)),"",VLOOKUP(C31,'マスタ設定'!$E$9:$F$31,2,FALSE)) | H31: =ROUND(E31*G31,0) -> 0
B32: =IF(C32="","",1+B31) | G32: =IF(ISERROR(VLOOKUP(C32,'マスタ設定'!$E$9:$F$31,2,FALSE)),"",VLOOKUP(C32,'マスタ設定'!$E$9:$F$31,2,FALSE)) | H32: =ROUND(E32*G32,0) -> 0
B34: [振込先] | D34: 銀行名 | G34: 合 計 | H34: =SUM(H15:H32) -> 18635
C35: 普通 | D35: 口座番号
C37: 名義 | D37: ○○○○
